{"css":"","framework":"duck-10.1.0","title":"Photo Booth 帮助","build_id":"5791af87680ce25121c2313f","quick_links":[],"icon":"..\/SharedGlobalArt\/AppIconDefault_PhotoBooth.png","sections":{},"birdseed_version":5,"toc":["pbhl2210774c","pbhlp3714a9d","pbhl9df7dfbb","pbhlp9bb7574","pbhlp2413768","pbhl5d9d9c82","pbhl9e53b62a","pbhlpcfe96cc"],"locale":"zh-cn","version":"10.12","source_schema":"apd-schema","enable_tracking":false,"platform":"mac","build_date":"2016.07.22-02:49:43","landing":"pbhlp32628","product":"photobooth","urls":{},"copyright":"","show_previous_next":false,"topics":{"pbhl9e53b62a":{"name":"共享照片和视频","searchName":"共享在 Photo Booth 中创建的照片和视频"},"pbhl5d9d9c82":{"name":"编辑照片和视频","searchName":"编辑在 Photo Booth 中创建的照片和视频"},"pbhlp32628":{"name":"Photo Booth 帮助","href":"pbhlp32628.html","categories":["landing"]},"pbhlp3714a9d":{"name":"拍照或录制视频","searchName":"使用 Photo Booth 拍照或录制视频"},"pbhl9df7dfbb":{"name":"应用效果和使用背景","searchName":"使用 Photo Booth 来应用效果或自定背景"},"pbhlp9bb7574":{"name":"查看照片和视频","searchName":"查看在 Photo Booth 中创建的照片和视频"},"pbhlpcfe96cc":{"name":"删除照片和视频","searchName":"删除在 Photo Booth 中创建的照片和视频"},"pbhl2210774c":{"name":"Photo Booth 概览"},"pbhle4881e6b":{"name":"更新个人头像","searchName":"使用 Photo Booth 为各种应用拍摄个人头像"},"pbhlp2413768":{"name":"存储照片和视频","searchName":"存储在 Photo Booth 中创建的照片和视频"}},"copyright_text":"Copyright © 2016 Apple Inc. 保留一切权利。"}